odoo/addons/ladirecta_res_partner_api/README.md
odoo/addons/ladirecta_res_partner_api/__init__.py
odoo/addons/ladirecta_res_partner_api/__manifest__.py
odoo/addons/ladirecta_res_partner_api/services/__init__.py
odoo/addons/ladirecta_res_partner_api/services/res_partner_service.py
odoo/addons/ladirecta_res_partner_api/services/schemas.py
odoo_addon_ladirecta_res_partner_api-16.0.1.1.0.dist-info/METADATA
odoo_addon_ladirecta_res_partner_api-16.0.1.1.0.dist-info/WHEEL
odoo_addon_ladirecta_res_partner_api-16.0.1.1.0.dist-info/top_level.txt
odoo_addon_ladirecta_res_partner_api-16.0.1.1.0.dist-info/RECORD
