Metadata-Version: 2.4
Name: odoo-addon-ladirecta_res_partner_api
Version: 16.0.1.1.0
Summary: La Directa Res Partner API
Home-page: https://git.coopdevs.org/talaios/addons/odoo-directa#
Author: Coopdevs Treball SCCL,
License: AGPL-3
Classifier: Programming Language :: Python
Classifier: Framework :: Odoo
Classifier: Framework :: Odoo :: 16.0
Classifier: License :: OSI Approved :: GNU Affero General Public License v3
Requires-Python: >=3.10
Requires-Dist: odoo-addon-api_common_base<16.1dev,>=16.0dev
Requires-Dist: odoo-addon-ladirecta<16.1dev,>=16.0dev
Requires-Dist: odoo<16.1dev,>=16.0a
Dynamic: author
Dynamic: classifier
Dynamic: home-page
Dynamic: license
Dynamic: requires-dist
Dynamic: requires-python
Dynamic: summary
